setup.py
django_snippet.egg-info/PKG-INFO
django_snippet.egg-info/SOURCES.txt
django_snippet.egg-info/dependency_links.txt
django_snippet.egg-info/top_level.txt
snippet/__init__.py
snippet/admin.py
snippet/models.py
snippet/tests.py
snippet/views.py
snippet/templatetags/__init__.py
snippet/templatetags/snippet.py